torch_fftconv/__init__.py
torch_fftconv/functional.py
torch_fftconv/modules.py
torch_fftconv/utils.py
torch_fftconv-0.1.3.dist-info/METADATA
torch_fftconv-0.1.3.dist-info/WHEEL
torch_fftconv-0.1.3.dist-info/top_level.txt
torch_fftconv-0.1.3.dist-info/RECORD
