Metadata-Version: 2.1
Name: torch-fftconv
Version: 0.1.3
Summary: Implementation of 1D, 2D, and 3D FFT convolutions in PyTorch. Much faster than direct convolutions for large kernel sizes
Home-page: https://github.com/yoyololicon/fft-conv-pytorch
Author: Chin-Yun Yu
Author-email: lolimaster.cs03@nctu.edu.tw
Classifier: Programming Language :: Python :: 3
Classifier: License :: OSI Approved :: MIT License
Classifier: Operating System :: OS Independent
Requires-Dist: torch (>=1.7.0)
